ed25519_axolotl-1.7.0.dist-info/METADATA
ed25519_axolotl-1.7.0.dist-info/WHEEL
ed25519_axolotl/__init__.py
ed25519_axolotl/ed25519_axolotl.cpython-39-aarch64-linux-gnu.so
ed25519_axolotl-1.7.0.dist-info/RECORD
