Metadata-Version: 2.1
Name: ed25519-axolotl
Version: 1.7.0
Summary: Ed25519-like signatures with X25519 keys, Axolotl-style.
Keywords: ed25519,axolotl,lunes,cryptography,cryptocurrencies
License: MIT
Project-URL: Source Code, https://github.com/lunes-platform/ed25519-axolotl.git
